mowlib
