Metadata-Version: 1.1
Name: mow
Version: 0.0.8
Summary: Organise your movie folders, fetch metadata and movie-posters
Home-page: UNKNOWN
Author: Chris Patrick Schreiner
Author-email: schpaencoder@gmail.com
License: MIT
Keywords: utility archive catalog movie
Platform: any
Classifier: Development Status :: 3 - Alpha
Classifier: Natural Language :: English
Classifier: Operating System :: OS Independent
Classifier: Programming Language :: Python :: 3.5
Classifier: License :: OSI Approved :: MIT License
Classifier: Topic :: Desktop Environment :: File Managers
Classifier: Topic :: Internet
Classifier: Topic :: Multimedia :: Video
Classifier: Topic :: Database
Classifier: Topic :: Home Automation
Classifier: Topic :: System :: Archiving :: Backup
Classifier: Topic :: Utilities
Classifier: Intended Audience :: End Users/Desktop
